word2vec_matryoshka/__init__.py
word2vec_matryoshka/_core.abi3.so
word2vec_matryoshka/_docs_examples.py
word2vec_matryoshka/_streaming_examples.py
word2vec_matryoshka/typing.pyi
word2vec_matryoshka.libs/libgcc_s-0cd532bd.so.1
word2vec_matryoshka-0.1.5.dist-info/METADATA
word2vec_matryoshka-0.1.5.dist-info/WHEEL
word2vec_matryoshka-0.1.5.dist-info/RECORD
word2vec_matryoshka-0.1.5.dist-info/licenses/LICENSE
