Metadata-Version: 2.4
Name: word2vec-matryoshka
Version: 0.1.5
Requires-Dist: numpy>=1.26
Requires-Dist: pytest>=8 ; extra == 'dev'
Requires-Dist: ruff>=0.6 ; extra == 'dev'
Requires-Dist: maturin>=1.5 ; extra == 'dev'
Provides-Extra: dev
License-File: LICENSE
Summary: Word2Vec with Matryoshka Representation Learning (Rust+PyO3), gensim-style API, numpy interop.
Author: Kelvin Liang
License: MIT
Requires-Python: >=3.10
